slowmo/Status.py
slowmo/Task.py
slowmo/TaskTree.py
slowmo/__init__.py
slowmo/draw.py
slowmo/terminal.py
slowmo-0.1.0.dist-info/WHEEL
slowmo-0.1.0.dist-info/METADATA
slowmo-0.1.0.dist-info/RECORD
